fissix/Grammar.txt
fissix/PatternGrammar.txt
fissix/__init__.py
fissix/__main__.py
fissix/__version__.py
fissix/btm_matcher.py
fissix/btm_utils.py
fissix/fixer_base.py
fissix/fixer_util.py
fissix/main.py
fissix/patcomp.py
fissix/pygram.py
fissix/pytree.py
fissix/refactor.py
fissix/fixes/__init__.py
fissix/fixes/fix_apply.py
fissix/fixes/fix_asserts.py
fissix/fixes/fix_basestring.py
fissix/fixes/fix_buffer.py
fissix/fixes/fix_dict.py
fissix/fixes/fix_except.py
fissix/fixes/fix_exec.py
fissix/fixes/fix_execfile.py
fissix/fixes/fix_exitfunc.py
fissix/fixes/fix_filter.py
fissix/fixes/fix_funcattrs.py
fissix/fixes/fix_future.py
fissix/fixes/fix_getcwdu.py
fissix/fixes/fix_has_key.py
fissix/fixes/fix_idioms.py
fissix/fixes/fix_import.py
fissix/fixes/fix_imports.py
fissix/fixes/fix_imports2.py
fissix/fixes/fix_input.py
fissix/fixes/fix_intern.py
fissix/fixes/fix_isinstance.py
fissix/fixes/fix_itertools.py
fissix/fixes/fix_itertools_imports.py
fissix/fixes/fix_long.py
fissix/fixes/fix_map.py
fissix/fixes/fix_metaclass.py
fissix/fixes/fix_methodattrs.py
fissix/fixes/fix_ne.py
fissix/fixes/fix_next.py
fissix/fixes/fix_nonzero.py
fissix/fixes/fix_numliterals.py
fissix/fixes/fix_operator.py
fissix/fixes/fix_paren.py
fissix/fixes/fix_print.py
fissix/fixes/fix_raise.py
fissix/fixes/fix_raw_input.py
fissix/fixes/fix_reduce.py
fissix/fixes/fix_reload.py
fissix/fixes/fix_renames.py
fissix/fixes/fix_repr.py
fissix/fixes/fix_set_literal.py
fissix/fixes/fix_sorted.py
fissix/fixes/fix_standarderror.py
fissix/fixes/fix_sys_exc.py
fissix/fixes/fix_throw.py
fissix/fixes/fix_tuple_params.py
fissix/fixes/fix_types.py
fissix/fixes/fix_unicode.py
fissix/fixes/fix_urllib.py
fissix/fixes/fix_ws_comma.py
fissix/fixes/fix_xrange.py
fissix/fixes/fix_xreadlines.py
fissix/fixes/fix_zip.py
fissix/pgen2/__init__.py
fissix/pgen2/conv.py
fissix/pgen2/driver.py
fissix/pgen2/grammar.py
fissix/pgen2/literals.py
fissix/pgen2/parse.py
fissix/pgen2/pgen.py
fissix/pgen2/token.py
fissix/pgen2/tokenize.py
fissix-21.6.6.dist-info/LICENSE
fissix-21.6.6.dist-info/WHEEL
fissix-21.6.6.dist-info/METADATA
fissix-21.6.6.dist-info/RECORD
