Metadata-Version: 2.1
Name: fissix
Version: 21.6.6
Summary: Monkeypatches to override default behavior of lib2to3.
Home-page: https://github.com/jreese/fissix
Author: John Reese
Author-email: john@noswap.com
Requires-Python: >=3.6
Classifier: Development Status :: 5 - Production/Stable
Classifier: Intended Audience :: Developers
Classifier: License :: OSI Approved :: Python Software Foundation License
Classifier: Topic :: Software Development :: Libraries
Requires-Dist: appdirs
